linkscape/__init__.py
linkscape/network.py
linkscape/template.html
link_scape-0.0.3.dist-info/LICENSE
link_scape-0.0.3.dist-info/METADATA
link_scape-0.0.3.dist-info/WHEEL
link_scape-0.0.3.dist-info/top_level.txt
link_scape-0.0.3.dist-info/RECORD
