Metadata-Version: 2.1
Name: link-scape
Version: 0.0.3
Summary: Python library to plot force-directed graphs.
Home-page: https://github.com/aloneguid/linkscape
Author: Ivan Gavryliuk
Author-email: ifs5vh19k@mozmail.com
License: Apache-2.0
License-File: LICENSE
